ChemGAPP_Package/ChemGAPP_Big/Add_Gene_Names.py
ChemGAPP_Package/ChemGAPP_Big/Bar_Plot_Conditions.py
ChemGAPP_Package/ChemGAPP_Big/Bar_Plot_Plates.py
ChemGAPP_Package/ChemGAPP_Big/Check_Normalisation.py
ChemGAPP_Package/ChemGAPP_Big/Condition_Variance.py
ChemGAPP_Package/ChemGAPP_Big/Cosine_Similarity.py
ChemGAPP_Package/ChemGAPP_Big/Iris_to_Dataset.py
ChemGAPP_Package/ChemGAPP_Big/MW_Conditions_to_Remove.py
ChemGAPP_Package/ChemGAPP_Big/MW_Plates_to_Remove.py
ChemGAPP_Package/ChemGAPP_Big/Mann_Whitney_Condition_Level.py
ChemGAPP_Package/ChemGAPP_Big/Mann_Whitney_Plate_Level.py
ChemGAPP_Package/ChemGAPP_Big/Pass_Fail_Conditions.py
ChemGAPP_Package/ChemGAPP_Big/Pass_Fail_Plates.py
ChemGAPP_Package/ChemGAPP_Big/S_Scores.py
ChemGAPP_Package/ChemGAPP_Big/Variance_Conditions_to_Remove.py
ChemGAPP_Package/ChemGAPP_Big/Z_Plates_to_Remove.py
ChemGAPP_Package/ChemGAPP_Big/Z_Score.py
ChemGAPP_Package/ChemGAPP_Big/Z_Score_Count.py
ChemGAPP_Package/ChemGAPP_Big/__init__.py
ChemGAPP_Package/ChemGAPP_GI/GI_Barplot.py
ChemGAPP_Package/ChemGAPP_GI/GI_Dataset.py
ChemGAPP_Package/ChemGAPP_GI/__init__.py
ChemGAPP_Package/ChemGAPP_Small/ChemGAPP_Small.py
ChemGAPP_Package/ChemGAPP_Small/__init__.py
ChemGAPP-0.0.9.dist-info/LICENSE
ChemGAPP-0.0.9.dist-info/METADATA
ChemGAPP-0.0.9.dist-info/WHEEL
ChemGAPP-0.0.9.dist-info/entry_points.txt
ChemGAPP-0.0.9.dist-info/top_level.txt
ChemGAPP-0.0.9.dist-info/RECORD
