Metadata-Version: 2.1
Name: ChemGAPP
Version: 0.0.9
Summary: A package for the analysis of chemical genomic screen data
Home-page: https://github.com/HannahMDoherty/ChemGAPP
Author: Hannah May Doherty
Author-email: hxd476@student.bham.ac.uk
License: by-nc-nd-4.0
Project-URL: Source, https://github.com/HannahMDoherty/ChemGAPP
Classifier: License :: Other/Proprietary License
Classifier: Intended Audience :: Science/Research
Classifier: Programming Language :: Python :: 3.7
Classifier: Programming Language :: Python :: 3.8
Classifier: Programming Language :: Python :: 3.9
Requires-Python: >=3.7
License-File: LICENSE
Requires-Dist: streamlit (==1.10.0)
Requires-Dist: seaborn (==0.11.2)
Requires-Dist: matplotlib (==3.6.0)
Requires-Dist: scikit-learn (==0.24.1)
Requires-Dist: more-itertools (==8.7.0)
Requires-Dist: pathlib2 (==2.3.5)
Requires-Dist: scipy (==1.6.2)
Requires-Dist: regex (==2022.9.13)
Requires-Dist: random2 (==1.0.1)
Requires-Dist: pickle-mixin (==1.0.2)
Requires-Dist: bioinfokit (==2.1.0)
Requires-Dist: statannotations (==0.4.4)
